{
  "Cutlass": [],
  "Dual Katana": [],
  "Katana": [],
  "Iron Mace": [],
  "Shark Saw": [],
  "Triple Katana": [],
  "Twin Hooks": [],
  "Dragon Trident": ["dt"],
  "Dual-Headed Blade": [],
  "Flail": ["jitte"],
  "Gravity Blade": ["grav blade", "gravity cane"],
  "Longsword": [],
  "Pipe": [],
  "Soul Cane": [],
  "Trident": [],
  "Wardens Sword": [],
  "Bisento": [],
  "Buddy Sword": [],
  "Canvander": [],
  "Dark Dagger": ["dd"],
  "Dragonheart": [],
  "Fox Lamp": [],
  "Koko": [],
  "Midnight Blade": [],
  "Oroshi": ["wando"],
  "Pole (1st Form)": [],
  "Pole (2nd Form)": ["pole v2"],
  "Rengoku": [],
  "Saber": [],
  "Saishi": ["saddi"],
  "Shark Anchor": ["anchor"],
  "Shizu": ["shisui"],
  "Spikey Trident": ["spikey"],
  "Tushita": [],
  "Yama": [],
  "Cursed Dual Katana": ["cdk"],
  "Dark Blade": ["db"],
  "Hallow Scythe": ["scythe"],
  "True Triple Katana" : ["ttk"],
  "Triple Dark Blade": ["ttg"]
}